{
  "concept": "(lambda (map (lambda (if (is_even $0) (* 3 $0) $0)) $0))",
  "examples": [
    { "i": [4, 95, 95, 0, 9], "o": [12, 95, 95, 0, 9] },
    { "i": [97, 8, 1, 53, 61, 3, 32, 11, 4], "o": [97, 24, 1, 53, 61, 3, 96, 11, 12] },
    { "i": [7, 67, 6, 6, 67, 2, 6, 7, 2, 2], "o": [7, 67, 18, 18, 67, 6, 18, 7, 6, 6] },
    { "i": [2, 26, 2, 26], "o": [6, 78, 6, 78] },
    { "i": [6, 19, 19, 8, 8, 8], "o": [18, 19, 19, 24, 24, 24] },
    { "i": [93, 20, 20], "o": [93, 60, 60] },
    { "i": [8, 4], "o": [24, 12] },
    { "i": [26], "o": [78] },
    { "i": [8, 2, 7, 22, 19, 9, 22, 0, 69], "o": [24, 6, 7, 66, 19, 9, 66, 0, 69] },
    { "i": [5, 4, 31, 6, 23, 8, 2, 63], "o": [5, 12, 31, 18, 23, 24, 6, 63] },
    { "i": [3, 3, 19, 19, 7, 2, 3], "o": [3, 3, 19, 19, 7, 6, 3] }
  ]
}
