{"concept": "(lambda (singleton (product (filter (lambda (== (% $0 4) 1)) $0))))", "examples": [{"i": [30, 14, 30, 2, 30, 86, 30, 86], "o": [1]}, {"i": [5, 56, 56, 56], "o": [5]}, {"i": [], "o": [1]}, {"i": [1, 30, 30, 99, 7, 40, 30, 1, 57], "o": [57]}, {"i": [57], "o": [57]}, {"i": [51, 91, 91, 84, 51, 42, 51, 51, 84], "o": [1]}, {"i": [63, 10, 34, 9, 2, 96], "o": [9]}, {"i": [2, 2, 1, 25, 6, 75, 7, 0, 62, 34], "o": [25]}, {"i": [94, 94, 94, 94, 5, 94], "o": [5]}, {"i": [42, 2, 7, 6, 0, 1, 6, 9, 3], "o": [9]}, {"i": [9, 9], "o": [81]}, {"i": [5, 43, 4, 1], "o": [5]}, {"i": [79, 3, 21], "o": [21]}, {"i": [12, 12, 6, 13], "o": [13]}, {"i": [5, 2, 5, 7, 34, 12], "o": [25]}, {"i": [41], "o": [41]}, {"i": [9, 9, 2], "o": [81]}, {"i": [5, 98, 7, 2, 5, 7, 7, 7, 7, 59], "o": [25]}, {"i": [6, 10, 14, 13, 78], "o": [13]}, {"i": [96, 62, 62, 10, 82, 3, 56, 52, 78, 9], "o": [9]}]}