{
  "concept": "(lambda (singleton (count (lambda (== 3 $0)) $0)))",
  "examples": [
    { "i": [2, 58, 2, 3, 1], "o": [1] },
    { "i": [7, 8, 66, 48, 91, 77], "o": [0] },
    { "i": [3, 4, 99, 54, 6, 59, 0, 9], "o": [1] },
    { "i": [0, 69, 69], "o": [0] },
    { "i": [3, 97, 3, 97, 97, 96, 96, 8], "o": [2] },
    { "i": [54, 30, 3, 93, 3, 54, 1], "o": [2] },
    { "i": [20, 28, 96, 70, 3, 28, 20, 96], "o": [1] },
    { "i": [24], "o": [0] },
    { "i": [38, 3, 55, 55, 64, 39], "o": [1] },
    { "i": [3, 52, 3, 4], "o": [2] },
    { "i": [57, 31, 0, 65, 13, 0, 9, 65, 5, 57], "o": [0] }
  ]
}
