{
  "concept": "(lambda (map (lambda (if (< $0 50) 99 (/ $0 8))) $0))",
  "examples": [
    { "i": [5, 29, 85, 0, 2, 0, 2], "o": [99, 99, 10, 99, 99, 99, 99] },
    { "i": [9, 72, 58, 59, 4, 10, 60, 82, 72], "o": [99, 9, 7, 7, 99, 99, 7, 10, 9] },
    { "i": [ ], "o": [ ] },
    { "i": [88, 88], "o": [11, 11] },
    { "i": [62, 18, 70, 22, 95, 9, 2, 5, 3, 93], "o": [7, 99, 8, 99, 11, 99, 99, 99, 99, 11] },
    { "i": [52, 14, 52, 14, 14, 52, 52, 14], "o": [6, 99, 6, 99, 99, 6, 6, 99] },
    { "i": [0, 10, 10], "o": [99, 99, 99] },
    { "i": [0, 0, 0, 4, 9, 0], "o": [99, 99, 99, 99, 99, 99] },
    { "i": [5, 8, 8, 27, 27, 8, 36, 36, 7], "o": [99, 99, 99, 99, 99, 99, 99, 99, 99] },
    { "i": [28, 6, 45, 6, 2, 11, 83], "o": [99, 99, 99, 99, 99, 99, 10] },
    { "i": [1, 65, 65, 65, 1, 65, 1, 57, 1, 1], "o": [99, 8, 8, 8, 99, 8, 99, 7, 99, 99] },
    { "i": [6, 95, 6, 45, 10], "o": [99, 11, 99, 99, 99] },
    { "i": [5, 3, 9, 3, 8, 29, 5, 7], "o": [99, 99, 99, 99, 99, 99, 99, 99] },
    { "i": [40, 4, 10, 4], "o": [99, 99, 99, 99] },
    { "i": [97, 97, 97, 97, 97, 97], "o": [12, 12, 12, 12, 12, 12] },
    { "i": [90, 9, 60, 76, 18, 5], "o": [11, 99, 7, 9, 99, 99] },
    { "i": [53, 53, 53, 53], "o": [6, 6, 6, 6] },
    { "i": [94, 94, 75, 94, 92, 81], "o": [11, 11, 9, 11, 11, 10] },
    { "i": [9, 46], "o": [99, 99] },
    { "i": [69], "o": [8] }
  ]
}
